GND/__init__.py
GND/get_parse.py
GND/AAGNN/AAGNN_A.py
GND/AAGNN/AAGNN_M.py
GND/AAGNN/__init__.py
GND/common/__init__.py
GND/common/dataset.py
GND/common/sample.py
GND/common/utils.py
GND/utils/__init__.py
GND/utils/print.py
GND/utils/utils.py
GND-0.1.1.dist-info/METADATA
GND-0.1.1.dist-info/WHEEL
GND-0.1.1.dist-info/top_level.txt
GND-0.1.1.dist-info/RECORD
