Metadata-Version: 2.1
Name: GND
Version: 0.1.1
Summary: GraphAnomalyDection Benchmarking using DGL
Home-page: UNKNOWN
Author: miziha-zp;zhoushengisnoob;GavinYGM;fmc123653;cfuser;Xinstein-rx
Author-email: fmc0315@126.com
License: apache 3.0
Platform: UNKNOWN
